pianoforte/__init__.py
pianoforte/admin.py
pianoforte/apps.py
pianoforte/models.py
pianoforte/tests.py
pianoforte/views.py
django_pianoforte-0.1.0.dist-info/LICENSE
django_pianoforte-0.1.0.dist-info/METADATA
django_pianoforte-0.1.0.dist-info/WHEEL
django_pianoforte-0.1.0.dist-info/top_level.txt
django_pianoforte-0.1.0.dist-info/RECORD
